<?xml version="1.0" encoding="UTF-8"?>
<BitmaskCfg>
    <GroupDecHexBin show="true"/>
    <Group32Bits show="false" hex_show="false"/>
    <GroupBitmask show="true">
        <Bit0 text="13313"/>
        <Bit1 text="4454"/>
        <Bit2 text="64654"/>
        <Bit3 text=""/>
        <Bit4 text=""/>
        <Bit5 text=""/>
        <Bit6 text=""/>
        <Bit7 text=""/>
        <Bit8 text=""/>
        <Bit9 text=""/>
        <Bit10 text=""/>
        <Bit11 text=""/>
        <Bit12 text=""/>
        <Bit13 text=""/>
        <Bit14 text=""/>
        <Bit15 text=""/>
        <Bit16 text=""/>
        <Bit17 text=""/>
        <Bit18 text=""/>
        <Bit19 text=""/>
        <Bit20 text=""/>
        <Bit21 text=""/>
        <Bit22 text=""/>
        <Bit23 text=""/>
        <Bit24 text=""/>
        <Bit25 text=""/>
        <Bit26 text=""/>
        <Bit27 text=""/>
        <Bit28 text=""/>
        <Bit29 text=""/>
        <Bit30 text=""/>
        <Bit31 text=""/>
    </GroupBitmask>
</BitmaskCfg>
